pynstein/__init__.py
pynstein/frame.py
pynstein/funcs.py
pynstein/fvec.py
pynstein/fvel.py
pynstein-0.2.0.dist-info/LICENSE.txt
pynstein-0.2.0.dist-info/METADATA
pynstein-0.2.0.dist-info/WHEEL
pynstein-0.2.0.dist-info/top_level.txt
pynstein-0.2.0.dist-info/RECORD
